[
  {
    "price": 299999.0,
    "seller": "Desconocido",
    "free_shipping": 0,
    "scraped_at": "2025-12-11T12:23:55.649957",
    "title": "Sin título"
  },
  {
    "price": 1354195.0,
    "seller": "Desconocido",
    "free_shipping": 0,
    "scraped_at": "2025-12-11T12:26:18.813257",
    "title": "Sin título"
  },
  {
    "price": 1732099.0,
    "seller": "Desconocido",
    "free_shipping": 0,
    "scraped_at": "2025-12-11T12:26:18.813667",
    "title": "Sin título"
  },
  {
    "price": 948370.0,
    "seller": "Desconocido",
    "free_shipping": 0,
    "scraped_at": "2025-12-11T12:26:18.813826",
    "title": "Sin título"
  },
  {
    "price": 28900.0,
    "seller": "Desconocido",
    "free_shipping": 0,
    "scraped_at": "2025-12-11T12:31:26.705453",
    "title": "Sin título"
  },
  {
    "price": 22000.0,
    "seller": "Desconocido",
    "free_shipping": 0,
    "scraped_at": "2025-12-11T12:32:04.912088",
    "title": "Sin título"
  },
  {
    "price": 28900.0,
    "seller": "Desconocido",
    "free_shipping": 0,
    "scraped_at": "2025-12-11T12:32:21.832275",
    "title": "Sin título"
  }
]